optunacy/__init__.py
optunacy/oplot.py
optunacy-0.3.3.dist-info/LICENSE
optunacy-0.3.3.dist-info/METADATA
optunacy-0.3.3.dist-info/WHEEL
optunacy-0.3.3.dist-info/RECORD
