Metadata-Version: 2.1
Name: optunacy
Version: 0.3.3
Summary: Optunacy is a contour plot generator for Optuna studies.
Home-page: https://github.com/retospect/optunacy
License: GPL-3
Keywords: optuna,contour,plot,snn,hyperparameter,optimization
Author: Reto Stamm
Maintainer: Reto Stamm
Requires-Python: >=3.9,<4.0
Classifier: License :: Other/Proprietary License
Classifier: Programming Language :: Python :: 3
Classifier: Programming Language :: Python :: 3.9
Classifier: Programming Language :: Python :: 3.10
Classifier: Programming Language :: Python :: 3.11
Classifier: Programming Language :: Python :: 3.12
Requires-Dist: matplotlib (>=3.8.2,<4.0.0)
Requires-Dist: numpy (>=1.26.2,<2.0.0)
Requires-Dist: optuna (>=3.4.0,<4.0.0)
Requires-Dist: plotly (>=5.18.0,<6.0.0)
Requires-Dist: scipy (>=1.11.4,<2.0.0)
Project-URL: Repository, https://github.com/retospect/optunacy
